LICENSE.txt
MANIFEST.in
README.md
setup.py
kip/__init__.py
kip/cli.py
kip/kip.conf
kip.egg-info/PKG-INFO
kip.egg-info/SOURCES.txt
kip.egg-info/dependency_links.txt
kip.egg-info/entry_points.txt
kip.egg-info/requires.txt
kip.egg-info/top_level.txt