Metadata-Version: 1.1
Name: kip
Version: 0.3.1
Summary: kip Keeps Passwords
Home-page: https://github.com/grahamking/kip
Author: Graham King
Author-email: graham@gkgk.org
License: UNKNOWN
Platform: UNKNOWN
Classifier: Development Status :: 4 - Beta
Classifier: Environment :: Console
Classifier: Intended Audience :: End Users/Desktop
Classifier: License :: OSI Approved :: GNU General Public License (GPL)
Classifier: Operating System :: OS Independent
Classifier: Programming Language :: Python
Classifier: Topic :: Utilities
